{
  "aluminium": {
    "price": 3035,
    "currency": "USD",
    "symbol": "MANUAL",
    "source": "Manuell",
    "notation": "USD/t",
    "unit": "t"
  },
  "fx": {
    "usdNok": {
      "pair": "USD/NOK",
      "rate": 9.4397,
      "date": "2026-04-15",
      "source": "Norges Bank"
    },
    "eurNok": {
      "pair": "EUR/NOK",
      "rate": 11.12,
      "date": "2026-04-15",
      "source": "Norges Bank"
    },
    "source": "Norges Bank"
  },
  "updatedAt": "2026-04-16T10:54:48.815Z",
  "mode": "auto-daily"
}